google/cloud/dataform/__init__.py
google/cloud/dataform/gapic_version.py
google/cloud/dataform/py.typed
google/cloud/dataform_v1/__init__.py
google/cloud/dataform_v1/gapic_metadata.json
google/cloud/dataform_v1/gapic_version.py
google/cloud/dataform_v1/py.typed
google/cloud/dataform_v1/services/__init__.py
google/cloud/dataform_v1/services/dataform/__init__.py
google/cloud/dataform_v1/services/dataform/async_client.py
google/cloud/dataform_v1/services/dataform/client.py
google/cloud/dataform_v1/services/dataform/pagers.py
google/cloud/dataform_v1/services/dataform/transports/__init__.py
google/cloud/dataform_v1/services/dataform/transports/base.py
google/cloud/dataform_v1/services/dataform/transports/grpc.py
google/cloud/dataform_v1/services/dataform/transports/grpc_asyncio.py
google/cloud/dataform_v1/services/dataform/transports/rest.py
google/cloud/dataform_v1/services/dataform/transports/rest_base.py
google/cloud/dataform_v1/types/__init__.py
google/cloud/dataform_v1/types/dataform.py
google/cloud/dataform_v1beta1/__init__.py
google/cloud/dataform_v1beta1/gapic_metadata.json
google/cloud/dataform_v1beta1/gapic_version.py
google/cloud/dataform_v1beta1/py.typed
google/cloud/dataform_v1beta1/services/__init__.py
google/cloud/dataform_v1beta1/services/dataform/__init__.py
google/cloud/dataform_v1beta1/services/dataform/async_client.py
google/cloud/dataform_v1beta1/services/dataform/client.py
google/cloud/dataform_v1beta1/services/dataform/pagers.py
google/cloud/dataform_v1beta1/services/dataform/transports/__init__.py
google/cloud/dataform_v1beta1/services/dataform/transports/base.py
google/cloud/dataform_v1beta1/services/dataform/transports/grpc.py
google/cloud/dataform_v1beta1/services/dataform/transports/grpc_asyncio.py
google/cloud/dataform_v1beta1/services/dataform/transports/rest.py
google/cloud/dataform_v1beta1/services/dataform/transports/rest_base.py
google/cloud/dataform_v1beta1/types/__init__.py
google/cloud/dataform_v1beta1/types/dataform.py
google_cloud_dataform-0.6.1.dist-info/LICENSE
google_cloud_dataform-0.6.1.dist-info/METADATA
google_cloud_dataform-0.6.1.dist-info/WHEEL
google_cloud_dataform-0.6.1.dist-info/top_level.txt
google_cloud_dataform-0.6.1.dist-info/RECORD
